{
  "users": [
    {
      "id": 1,
      "name": "John Doe",
      "email": "john@example.fr",
      "phone": "1234567890"
    },
    {
      "id": 2,
      "name": "Jane Smith",
      "email": "jane@example.com",
      "phone": "9876543210"
    },
    {
      "id": 3,
      "name": "Alice Johnson",
      "email": "alice@example.com",
      "phone": "555555555"
    },
    {
      "id": 4,
      "name": "LATER Yousra Zahra h",
      "email": "yousra.later@univ-constantine2.dz",
      "phone": "06670445"
    },
    {
      "id": 5,
      "name": "Lyna",
      "email": "lyna@gmail.com",
      "phone": "0445"
    },
    {
      "id": 6,
      "name": "Douaa",
      "email": "DL@gmail.com",
      "phone": "57756786786"
    },
    {
      "name": "Hannane",
      "email": "HanLyna@gmail.com",
      "phone": "02786576",
      "id": 7
    }
  ]
}